sixtools/AD_Handler.py
sixtools/GUI_components.py
sixtools/__init__.py
sixtools/_version.py
sixtools/plotting_functions.py
sixtools/rixs_wrapper.py
sixtools/tests/__init__.py
sixtools/tests/conftest.py
sixtools/tests/test_examples.py
sixtools-0.0.3.dist-info/AUTHORS.rst
sixtools-0.0.3.dist-info/LICENSE
sixtools-0.0.3.dist-info/METADATA
sixtools-0.0.3.dist-info/WHEEL
sixtools-0.0.3.dist-info/entry_points.txt
sixtools-0.0.3.dist-info/top_level.txt
sixtools-0.0.3.dist-info/RECORD
