Metadata-Version: 2.1
Name: sixtools
Version: 0.0.3
Summary: Software for performing resonant inelastic xray scattering analysis at NSLS-II
Home-page: https://github.com/awalter-bnl/sixtools
Author: Brookhaven National Lab
Author-email: awalter@bnl.gov
License: BSD (3-clause)
Platform: UNKNOWN
Classifier: Development Status :: 2 - Pre-Alpha
Classifier: Natural Language :: English
Classifier: Programming Language :: Python :: 3
Requires-Dist: databroker
Requires-Dist: ipywidgets
Requires-Dist: matplotlib
Requires-Dist: numpy
Requires-Dist: pandas
Requires-Dist: pims
Requires-Dist: rixs
Requires-Dist: scipy
